Metadata-Version: 2.1
Name: sqlUts
Version: 1.0.6
Summary: An orm package
Home-page: 
Author: Melque Lima
Author-email: melque_ex@yahoo.com.br
License: MIT
Keywords: sqlUts
Classifier: Development Status :: 5 - Production/Stable
Classifier: Intended Audience :: Education
Classifier: Operating System :: Microsoft :: Windows :: Windows 10
Classifier: License :: OSI Approved :: MIT License
Classifier: Programming Language :: Python :: 3
License-File: LICENCE.txt
Requires-Dist: SQLAlchemy<2.0.0
Requires-Dist: SQLAlchemy-Utils
